{
    "data": [
        {
            "id": 1,
            "firstName": "Sunny",
            "lastName": "Terese",
            "email": "sterese0@privacy.gov.au",
            "date": "11/01/2023",
            "favouriteMovie": "The Photographer",
            "Location": "Fos-sur-Mer"
        },
        {
            "id": 2,
            "firstName": "Giulio",
            "lastName": "Sarney",
            "email": "gsarney1@so-net.ne.jp",
            "date": "26/04/2022",
            "favouriteMovie": "Return of Martin Guerre, The (Retour de Martin Guerre, Le)",
            "Location": "União dos Palmares"
        },
        {
            "id": 3,
            "firstName": "Erwin",
            "lastName": "Durrett",
            "email": "edurrett2@homestead.com",
            "date": "13/03/2022",
            "favouriteMovie": "Britannia Hospital",
            "Location": "Gebre Guracha"
        },
        {
            "id": 4,
            "firstName": "Fionna",
            "lastName": "Siaspinski",
            "email": "fsiaspinski3@studiopress.com",
            "date": "11/12/2022",
            "favouriteMovie": "Suddenly (Tan de Repente)",
            "Location": "Līgatne"
        },
        {
            "id": 5,
            "firstName": "Kean",
            "lastName": "Wandtke",
            "email": "kwandtke4@google.de",
            "date": "30/07/2022",
            "favouriteMovie": "Nightbreed",
            "Location": "Gampang"
        },
        {
            "id": 6,
            "firstName": "Franciskus",
            "lastName": "De La Haye",
            "email": "fdelahaye5@foxnews.com",
            "date": "05/03/2022",
            "favouriteMovie": "Grey Zone, The",
            "Location": "Heshan"
        },
        {
            "id": 7,
            "firstName": "Rhona",
            "lastName": "Burnes",
            "email": "rburnes6@ask.com",
            "date": "10/05/2022",
            "favouriteMovie": "Amador",
            "Location": "Colorado Springs"
        },
        {
            "id": 8,
            "firstName": "Aldis",
            "lastName": "Tivenan",
            "email": "ativenan7@unblog.fr",
            "date": "26/08/2022",
            "favouriteMovie": "In A Day",
            "Location": "Sukoreno"
        },
        {
            "id": 9,
            "firstName": "Colan",
            "lastName": "Heel",
            "email": "cheel8@unesco.org",
            "date": "11/03/2022",
            "favouriteMovie": "Mammoth (Mammut)",
            "Location": "Sława"
        },
        {
            "id": 10,
            "firstName": "Neale",
            "lastName": "Regina",
            "email": "nregina9@elpais.com",
            "date": "03/06/2022",
            "favouriteMovie": "Return to Never Land",
            "Location": "Saparbay"
        }
    ]
}